qtile_bonsai/__init__.py
qtile_bonsai/core/__init__.py
qtile_bonsai/core/geometry.py
qtile_bonsai/core/nodes.py
qtile_bonsai/core/tree.py
qtile_bonsai/core/utils.py
qtile_bonsai/layout.py
qtile_bonsai/theme.py
qtile_bonsai/tree.py
qtile_bonsai/utils/__init__.py
qtile_bonsai/utils/config.py
qtile_bonsai/utils/process.py
qtile_bonsai/validation.py
qtile_bonsai/widget.py
qtile_bonsai-0.6.0.dist-info/WHEEL
qtile_bonsai-0.6.0.dist-info/METADATA
qtile_bonsai-0.6.0.dist-info/RECORD
