Metadata-Version: 2.3
Name: qtile-bonsai
Version: 0.6.0
Summary: A flexible custom layout for the qtile window manager that supports arbitrarily nestable tabs and splits.
Keywords: qtile,bonsai,tiling,window,manager,layout
Author: Aravinda Rao
Author-email: Aravinda Rao <maniacalace@gmail.com>
License: MIT
Classifier: Development Status :: 5 - Production/Stable
Classifier: License :: OSI Approved :: MIT License
Classifier: Programming Language :: Python :: 3 :: Only
Classifier: Programming Language :: Python :: 3.12
Classifier: Programming Language :: Python :: 3.13
Classifier: Programming Language :: Python :: Implementation :: CPython
Classifier: Programming Language :: Python :: Implementation :: PyPy
Classifier: Topic :: Desktop Environment :: Window Managers
Requires-Dist: psutil
Requires-Python: >=3.12
Project-URL: Documentation, https://github.com/aravinda0/qtile-bonsai#readme
Project-URL: Issues, https://github.com/aravinda0/qtile-bonsai/issues
Project-URL: Source, https://github.com/aravinda0/qtile-bonsai
Project-URL: Visual Guide, https://aravinda0.github.io/qtile-bonsai/static/visual_guide/
